[
  {
      "_id": "679fb3383d8490c80d05fe9d",
      "userId": "1",
      "name": "John Doe",
      "email": "john.doe@example.com",
      "password": "john123"
  },
  {
      "_id": "679fb3483d8490c80d05fe9f",
      "userId": "2",
      "name": "Jane Smith",
      "email": "jane.smith@example.com",
      "password": "jane123"
  },
  {
      "_id": "679fb3aa3d8490c80d05fea1",
      "userId": "3",
      "name": "Alice Brown",
      "email": "alice.brown@example.com",
      "password": "alice123"
  },
  {
      "_id": "679fb3c03d8490c80d05fea3",
      "userId": "4",
      "name": "Bob Johnson",
      "email": "bob.johnson@example.com",
      "password": "bob123"
  },
  {
      "_id": "679fb3c93d8490c80d05fea5",
      "userId": "5",
      "name": "Charlie Davis",
      "email": "charlie.davis@example.com",
      "password": "charlie123"
  },
  {
      "_id": "679fb3d13d8490c80d05fea7",
      "userId": "6",
      "name": "David Lee",
      "email": "david.lee@example.com",
      "password": "david123"
  },
  {
      "_id": "679fb3e13d8490c80d05fea9",
      "userId": "7",
      "name": "Eve White",
      "email": "eve.white@example.com",
      "password": "eve123"
  },
  {
      "_id": "679fb3f23d8490c80d05feab",
      "userId": "8",
      "name": "Frank Green",
      "email": "frank.green@example.com",
      "password": "frank123"
  },
  {
      "_id": "679fb3fa3d8490c80d05fead",
      "userId": "9",
      "name": "Grace Black",
      "email": "grace.black@example.com",
      "password": "grace123"
  },
  {
      "_id": "679fb4083d8490c80d05feaf",
      "userId": "10",
      "name": "Hannah Adams",
      "email": "hannah.adams@example.com",
      "password": "hannah123"
  },
  {
      "_id": "679fb4103d8490c80d05feb1",
      "userId": "11",
      "name": "Ivy Harris",
      "email": "ivy.harris@example.com",
      "password": "ivy123"
  },
  {
      "_id": "679fb4183d8490c80d05feb3",
      "userId": "12",
      "name": "Jack King",
      "email": "jack.king@example.com",
      "password": "jack123"
  },
  {
      "_id": "679fb4273d8490c80d05feb5",
      "userId": "13",
      "name": "Kathy Martinez",
      "email": "kathy.martinez@example.com",
      "password": "kathy123"
  },
  {
      "_id": "679fb46e3d8490c80d05feb8",
      "userId": "14",
      "name": "Leo Scott",
      "email": "leo.scott@example.com",
      "password": "leo123"
  },
  {
      "_id": "679fb47b3d8490c80d05feba",
      "userId": "15",
      "name": "Mia Wright",
      "email": "mia.wright@example.com",
      "password": "mia123"
  }
]